fastapi_pulse/__init__.py
fastapi_pulse/constants.py
fastapi_pulse/metrics.py
fastapi_pulse/middleware.py
fastapi_pulse/payload_store.py
fastapi_pulse/probe.py
fastapi_pulse/registry.py
fastapi_pulse/router.py
fastapi_pulse/sample_builder.py
fastapi_pulse/cli/__init__.py
fastapi_pulse/cli/__main__.py
fastapi_pulse/cli/commands.py
fastapi_pulse/cli/output.py
fastapi_pulse/cli/standalone_probe.py
fastapi_pulse/static/endpoints.html
fastapi_pulse/static/index.html
fastapi_pulse/static/css/dashboard.css
fastapi_pulse/static/js/api.js
fastapi_pulse/static/js/charts.js
fastapi_pulse/static/js/components.js
fastapi_pulse/static/js/dashboard.js
fastapi_pulse/static/js/endpoints.js
fastapi_pulse/static/js/utils.js
fastapi_pulse-0.2.0.dist-info/LICENSE
fastapi_pulse-0.2.0.dist-info/METADATA
fastapi_pulse-0.2.0.dist-info/WHEEL
fastapi_pulse-0.2.0.dist-info/entry_points.txt
fastapi_pulse-0.2.0.dist-info/top_level.txt
fastapi_pulse-0.2.0.dist-info/RECORD
