Metadata-Version: 2.1
Name: fastapi-pulse
Version: 0.2.0
Summary: Check your FastAPI's pulse with one line of code. Instant health monitoring and dashboard.
Author-email: Parham Davari <parham.davarii@gmail.com>
Project-URL: Homepage, https://github.com/parhamdavari/fastapi-pulse
Project-URL: Bug Tracker, https://github.com/parhamdavari/fastapi-pulse/issues
Classifier: Programming Language :: Python :: 3
Classifier: License :: OSI Approved :: MIT License
Classifier: Operating System :: OS Independent
Classifier: Framework :: FastAPI
Requires-Python: >=3.8
License-File: LICENSE
Requires-Dist: fastapi
Requires-Dist: tdigest >=0.5.2
Requires-Dist: httpx >=0.23.0
Provides-Extra: cli
Requires-Dist: click >=8.1.0 ; extra == 'cli'
Requires-Dist: rich >=13.0.0 ; extra == 'cli'
Requires-Dist: pyyaml >=6.0.0 ; extra == 'cli'
Provides-Extra: dev
Requires-Dist: uvicorn ; extra == 'dev'
Provides-Extra: test
Requires-Dist: pytest >=7.0.0 ; extra == 'test'
Requires-Dist: pytest-cov >=4.0.0 ; extra == 'test'
Requires-Dist: pytest-asyncio >=0.18.0 ; extra == 'test'
Requires-Dist: httpx >=0.23.0 ; extra == 'test'
Requires-Dist: numpy >=1.20.0 ; extra == 'test'
